cewler/cewler.py
cewler/config.py
cewler/constants.py
cewler/spider.py
cewler-1.4.1.dist-info/licenses/LICENSE
cewler-1.4.1.dist-info/METADATA
cewler-1.4.1.dist-info/WHEEL
cewler-1.4.1.dist-info/entry_points.txt
cewler-1.4.1.dist-info/top_level.txt
cewler-1.4.1.dist-info/RECORD
