Metadata-Version: 2.4
Name: cewler
Version: 1.4.1
Summary: Custom Word List generator Redefined
Author-email: Roy Solberg <pypi-0q238r@roysolberg.com>
License-Expression: CC-BY-NC-4.0
Project-URL: Homepage, https://github.com/roys/cewler
Project-URL: Bug Tracker, https://github.com/roys/cewler/issues
Project-URL: Changelog, https://github.com/roys/cewler/blob/main/CHANGELOG.md
Keywords: custom wordlist,wordlist generator,bug bounty hunting,security testing,pen testing,crawler,spider
Classifier: Programming Language :: Python :: 3
Classifier: Operating System :: OS Independent
Classifier: Topic :: Security
Classifier: Topic :: Internet :: WWW/HTTP :: Indexing/Search
Classifier: Development Status :: 5 - Production/Stable
Classifier: Environment :: Console
Classifier: Framework :: Scrapy
Classifier: Intended Audience :: Information Technology
Classifier: Natural Language :: English
Requires-Python: >=3.9
License-File: LICENSE
Requires-Dist: pypdf~=6.1.1
Requires-Dist: rich~=14.2.0
Requires-Dist: Scrapy~=2.13.3
Requires-Dist: tld~=0.13.1
Dynamic: license-file
